data_processing_block.v
`timescale 1ns / 1ps

module data_processing_block (
    input              clk,
    input              rst,

    input              valid_in,
    output             ready_in,
    input      [7:0]   data_in,
    input      [1:0]   mode,

    output             valid_out,
    input              ready_out,
    output     [7:0]   data_out
);

    reg [7:0] data_reg;
    reg       valid_reg;

    // Ready/Valid handshake logic
    assign ready_in  = (~valid_reg) | ready_out;
    assign valid_out = valid_reg;
    assign data_out  = data_reg;

    always @(posedge clk) begin
        if (rst) begin
            data_reg  <= 8'b0;
            valid_reg <= 1'b0;
        end else begin
            if (valid_in && ready_in) begin
                valid_reg <= 1'b1;
                case (mode)
                    2'b00: data_reg <= data_in;           // Bypass
                    2'b01: data_reg <= data_in + 8'd1;    // Increment
                    2'b10: data_reg <= ~data_in;          // Invert
                    2'b11: data_reg <= data_in << 1;      // Gain x2
                    default: data_reg <= data_in;
                endcase
            end else if (ready_out) begin
                valid_reg <= 1'b0;
            end
        end
    end

endmodule

data_producing_block.v
`timescale 1ns / 1ps

module data_producing_block (
    input            clk,
    input            rst,
    output reg       valid_out,
    input            ready_in,
    output reg [7:0] data_out
);

    always @(posedge clk) begin
        if (rst) begin
            valid_out <= 1'b0;
            data_out  <= 8'd0;
        end
        else begin
            if (ready_in) begin
                valid_out <= 1'b1;
                data_out  <= data_out + 8'd1;
            end
            // else: hold current valid_out and data_out
        end
    end

endmodule

data_prod_proc.v
`timescale 1ns / 1ps

module data_prod_proc (
    input        clk,
    input        rst,
    input  [1:0] mode,
    output       valid_out,
    input        ready_out,
    output [7:0] data_out
);

    wire        prod_valid;
    wire        prod_ready;
    wire [7:0]  prod_data;

    // Producer
    data_producing_block producer (
        .clk       (clk),
        .rst       (rst),
        .valid_out (prod_valid),
        .ready_in  (prod_ready),
        .data_out  (prod_data)
    );

    // Processor
    data_processing_block processor (
        .clk       (clk),
        .rst       (rst),
        .valid_in  (prod_valid),
        .ready_in  (prod_ready),
        .data_in   (prod_data),
        .mode      (mode),
        .valid_out (valid_out),
        .ready_out (ready_out),
        .data_out  (data_out)
    );

endmodule

tb_data_prod_proc.v
`timescale 1ns / 1ps

module tb_data_prod_proc;

    reg         clk;
    reg         rst;
    reg  [1:0]  mode;
    reg         ready_out;
    wire        valid_out;
    wire [7:0]  data_out;

    // DUT
    data_prod_proc dut (
        .clk       (clk),
        .rst       (rst),
        .mode      (mode),
        .valid_out (valid_out),
        .ready_out (ready_out),
        .data_out  (data_out)
    );

    // Clock generation: 10 ns period
    always #5 clk = ~clk;

    initial begin
        // Dump waves
        $dumpfile("data_prod_proc.vcd");
        $dumpvars(0, tb_data_prod_proc);

        // Init
        clk       = 0;
        rst       = 1;
        mode      = 2'b00;
        ready_out = 0;

        // Reset pulse
        #20;
        rst = 0;

        // Enable downstream ready
        #10;
        ready_out = 1;

        // Change modes over time
        #50 mode = 2'b01; // increment
        #50 mode = 2'b10; // invert
        #50 mode = 2'b11; // shift left

        // Apply backpressure
        #40 ready_out = 0;
        #30 ready_out = 1;

        // Finish
        #100;
        $finish;
    end

endmodule

data_prod_proc.vcd
$date
	Sun Feb  8 16:34:06 2026
$end
$version
	Icarus Verilog
$end
$timescale
	1ps
$end
$scope module tb_data_prod_proc $end
$var wire 1 ! valid_out $end
$var wire 8 " data_out [7:0] $end
$var reg 1 # clk $end
$var reg 2 $ mode [1:0] $end
$var reg 1 % ready_out $end
$var reg 1 & rst $end
$scope module dut $end
$var wire 1 # clk $end
$var wire 2 ' mode [1:0] $end
$var wire 1 % ready_out $end
$var wire 1 & rst $end
$var wire 1 ! valid_out $end
$var wire 1 ( prod_valid $end
$var wire 1 ) prod_ready $end
$var wire 8 * prod_data [7:0] $end
$var wire 8 + data_out [7:0] $end
$scope module processor $end
$var wire 1 # clk $end
$var wire 8 , data_out [7:0] $end
$var wire 2 - mode [1:0] $end
$var wire 1 ) ready_in $end
$var wire 1 % ready_out $end
$var wire 1 & rst $end
$var wire 1 ! valid_out $end
$var wire 1 ( valid_in $end
$var wire 8 . data_in [7:0] $end
$var reg 8 / data_reg [7:0] $end
$var reg 1 0 valid_reg $end
$upscope $end
$scope module producer $end
$var wire 1 # clk $end
$var wire 1 ) ready_in $end
$var wire 1 & rst $end
$var reg 8 1 data_out [7:0] $end
$var reg 1 ( valid_out $end
$upscope $end
$upscope $end
$upscope $end
$enddefinitions $end
$comment Show the parameter values. $end
$dumpall
$end
#0
$dumpvars
bx 1
x0
bx /
bx .
b0 -
bx ,
bx +
bx *
x)
x(
b0 '
1&
0%
b0 $
0#
bx "
x!
$end
#5000
1)
b0 *
b0 .
b0 1
0(
0!
00
b0 "
b0 +
b0 ,
b0 /
1#
#10000
0#
#15000
1#
#20000
0#
0&
#25000
b1 *
b1 .
b1 1
1(
1#
#30000
0#
1%
#35000
b1 "
b1 +
b1 ,
b1 /
1!
10
b10 *
b10 .
b10 1
1#
#40000
0#
#45000
b11 *
b11 .
b11 1
b10 "
b10 +
b10 ,
b10 /
1#
#50000
0#
#55000
b11 "
b11 +
b11 ,
b11 /
b100 *
b100 .
b100 1
1#
#60000
0#
#65000
b101 *
b101 .
b101 1
b100 "
b100 +
b100 ,
b100 /
1#
#70000
0#
#75000
b101 "
b101 +
b101 ,
b101 /
b110 *
b110 .
b110 1
1#
#80000
0#
b1 $
b1 '
b1 -
#85000
b111 *
b111 .
b111 1
b111 "
b111 +
b111 ,
b111 /
1#
#90000
0#
#95000
b1000 "
b1000 +
b1000 ,
b1000 /
b1000 *
b1000 .
b1000 1
1#
#100000
0#
#105000
b1001 *
b1001 .
b1001 1
b1001 "
b1001 +
b1001 ,
b1001 /
1#
#110000
0#
#115000
b1010 "
b1010 +
b1010 ,
b1010 /
b1010 *
b1010 .
b1010 1
1#
#120000
0#
#125000
b1011 *
b1011 .
b1011 1
b1011 "
b1011 +
b1011 ,
b1011 /
1#
#130000
0#
b10 $
b10 '
b10 -
#135000
b11110100 "
b11110100 +
b11110100 ,
b11110100 /
b1100 *
b1100 .
b1100 1
1#
#140000
0#
#145000
b1101 *
b1101 .
b1101 1
b11110011 "
b11110011 +
b11110011 ,
b11110011 /
1#
#150000
0#
#155000
b11110010 "
b11110010 +
b11110010 ,
b11110010 /
b1110 *
b1110 .
b1110 1
1#
#160000
0#
#165000
b1111 *
b1111 .
b1111 1
b11110001 "
b11110001 +
b11110001 ,
b11110001 /
1#
#170000
0#
#175000
b11110000 "
b11110000 +
b11110000 ,
b11110000 /
b10000 *
b10000 .
b10000 1
1#
#180000
0#
b11 $
b11 '
b11 -
#185000
b10001 *
b10001 .
b10001 1
b100000 "
b100000 +
b100000 ,
b100000 /
1#
#190000
0#
#195000
b100010 "
b100010 +
b100010 ,
b100010 /
b10010 *
b10010 .
b10010 1
1#
#200000
0#
#205000
b10011 *
b10011 .
b10011 1
b100100 "
b100100 +
b100100 ,
b100100 /
1#
#210000
0#
#215000
b100110 "
b100110 +
b100110 ,
b100110 /
b10100 *
b10100 .
b10100 1
1#
#220000
0)
0#
0%
#225000
1#
#230000
0#
#235000
1#
#240000
0#
#245000
1#
#250000
1)
0#
1%
#255000
b101000 "
b101000 +
b101000 ,
b101000 /
b10101 *
b10101 .
b10101 1
1#
#260000
0#
#265000
b10110 *
b10110 .
b10110 1
b101010 "
b101010 +
b101010 ,
b101010 /
1#
#270000
0#
#275000
b101100 "
b101100 +
b101100 ,
b101100 /
b10111 *
b10111 .
b10111 1
1#
#280000
0#
#285000
b11000 *
b11000 .
b11000 1
b101110 "
b101110 +
b101110 ,
b101110 /
1#
#290000
0#
#295000
b110000 "
b110000 +
b110000 ,
b110000 /
b11001 *
b11001 .
b11001 1
1#
#300000
0#
#305000
b11010 *
b11010 .
b11010 1
b110010 "
b110010 +
b110010 ,
b110010 /
1#
#310000
0#
#315000
b110100 "
b110100 +
b110100 ,
b110100 /
b11011 *
b11011 .
b11011 1
1#
#320000
0#
#325000
b11100 *
b11100 .
b11100 1
b110110 "
b110110 +
b110110 ,
b110110 /
1#
#330000
0#
#335000
b111000 "
b111000 +
b111000 ,
b111000 /
b11101 *
b11101 .
b11101 1
1#
#340000
0#
#345000
b11110 *
b11110 .
b11110 1
b111010 "
b111010 +
b111010 ,
b111010 /
1#
