data_processing_block.v
`timescale 1ns / 1ps

module data_processing_block (
    input              clk,
    input              rst,

    input              valid_in,
    output             ready_in,
    input      [7:0]   data_in,
    input      [1:0]   mode,

    output             valid_out,
    input              ready_out,
    output     [7:0]   data_out
);

    reg [7:0] data_reg;
    reg       valid_reg;

    // Ready/Valid handshake logic
    assign ready_in  = (~valid_reg) | ready_out;
    assign valid_out = valid_reg;
    assign data_out  = data_reg;

    always @(posedge clk) begin
        if (rst) begin
            data_reg  <= 8'b0;
            valid_reg <= 1'b0;
        end else begin
            if (valid_in && ready_in) begin
                valid_reg <= 1'b1;
                case (mode)
                    2'b00: data_reg <= data_in;           // Bypass
                    2'b01: data_reg <= data_in + 8'd1;    // Increment
                    2'b10: data_reg <= ~data_in;          // Invert
                    2'b11: data_reg <= data_in << 1;      // Gain x2
                    default: data_reg <= data_in;
                endcase
            end else if (ready_out) begin
                valid_reg <= 1'b0;
            end
        end
    end

endmodule

data_producing_block.v
`timescale 1ns / 1ps

module data_producing_block (
    input            clk,
    input            rst,
    output reg       valid_out,
    input            ready_in,
    output reg [7:0] data_out
);

    always @(posedge clk) begin
        if (rst) begin
            valid_out <= 1'b0;
            data_out  <= 8'd0;
        end
        else begin
            if (ready_in) begin
                valid_out <= 1'b1;
                data_out  <= data_out + 8'd1;
            end
            // else: hold current valid_out and data_out
        end
    end

endmodule

data_prod_proc.v
`timescale 1ns / 1ps

module data_prod_proc (
    input        clk,
    input        rst,
    input  [1:0] mode,
    input        bypass_en,   // NEW
    output       valid_out,
    input        ready_out,
    output [7:0] data_out
);

    wire        prod_valid;
    wire        prod_ready;
    wire [7:0]  prod_data;

    wire        proc_valid;
    wire [7:0]  proc_data;

    // Producer
    data_producing_block producer (
        .clk       (clk),
        .rst       (rst),
        .valid_out (prod_valid),
        .ready_in  (prod_ready),
        .data_out  (prod_data)
    );

    // Processor
    data_processing_block processor (
        .clk       (clk),
        .rst       (rst),
        .valid_in  (prod_valid),
        .ready_in  (prod_ready),
        .data_in   (prod_data),
        .mode      (mode),
        .valid_out (proc_valid),
        .ready_out (ready_out),
        .data_out  (proc_data)
    );

    assign valid_out = bypass_en ? prod_valid : proc_valid;
    assign data_out  = bypass_en ? prod_data  : proc_data;

    assign prod_ready = ready_out;

endmodule

tb_data_prod_proc.v
`timescale 1ns / 1ps

module tb_data_prod_proc;

    reg         clk;
    reg         rst;
    reg  [1:0]  mode;
    reg         ready_out;
    reg         bypass_en;

    wire        valid_out;
    wire [7:0]  data_out;

    // DUT
    data_prod_proc dut (
        .clk       (clk),
        .rst       (rst),
        .mode      (mode),
        .bypass_en (bypass_en),
        .valid_out (valid_out),
        .ready_out (ready_out),
        .data_out  (data_out)
    );

    // Clock generation: 10 ns period
    always #5 clk = ~clk;

    initial begin
        // Dump waves (INCLUDING INTERNAL DATA)
        $dumpfile("data_prod_proc.vcd");
        $dumpvars(0, tb_data_prod_proc);

        // Explicit internal signals for waveform clarity
        $dumpvars(1,
            clk,
            rst,
            mode,
            bypass_en,
            ready_out,
            valid_out,
            data_out,
            dut.prod_data,
            dut.proc_data,
            dut.prod_valid
        );

        // Initialization
        clk       = 0;
        rst       = 1;
        mode      = 2'b00;
        ready_out = 0;
        bypass_en = 0;

        // Reset
        #20 rst = 0;

        // Enable downstream ready
        #10 ready_out = 1;

        // Normal processing modes
        #50 mode = 2'b01; // increment
        #50 mode = 2'b10; // invert

        // Enable BYPASS
        #40 bypass_en = 1;

        // Disable BYPASS, change mode
        #60 bypass_en = 0;
            mode = 2'b11; // shift left

        // Apply backpressure
        #40 ready_out = 0;
        #30 ready_out = 1;

        #100 $finish;
    end

endmodule

data_prod_proc.vcd
$date
	Sun Feb  8 23:30:07 2026
$end
$version
	Icarus Verilog
$end
$timescale
	1ps
$end
$scope module tb_data_prod_proc $end
$var wire 1 ! valid_out $end
$var wire 8 " data_out [7:0] $end
$var reg 1 # bypass_en $end
$var reg 1 $ clk $end
$var reg 2 % mode [1:0] $end
$var reg 1 & ready_out $end
$var reg 1 ' rst $end
$scope module dut $end
$var wire 1 # bypass_en $end
$var wire 1 $ clk $end
$var wire 2 ( mode [1:0] $end
$var wire 1 ) prod_ready $end
$var wire 1 & ready_out $end
$var wire 1 ' rst $end
$var wire 1 ! valid_out $end
$var wire 1 * prod_valid $end
$var wire 8 + prod_data [7:0] $end
$var wire 1 , proc_valid $end
$var wire 8 - proc_data [7:0] $end
$var wire 8 . data_out [7:0] $end
$scope module processor $end
$var wire 1 $ clk $end
$var wire 2 / mode [1:0] $end
$var wire 1 ) ready_in $end
$var wire 1 & ready_out $end
$var wire 1 ' rst $end
$var wire 1 , valid_out $end
$var wire 1 * valid_in $end
$var wire 8 0 data_out [7:0] $end
$var wire 8 1 data_in [7:0] $end
$var reg 8 2 data_reg [7:0] $end
$var reg 1 3 valid_reg $end
$upscope $end
$scope module producer $end
$var wire 1 $ clk $end
$var wire 1 ) ready_in $end
$var wire 1 ' rst $end
$var reg 8 4 data_out [7:0] $end
$var reg 1 * valid_out $end
$upscope $end
$upscope $end
$upscope $end
$enddefinitions $end
$comment Show the parameter values. $end
$dumpall
$end
#0
$dumpvars
bx 4
x3
bx 2
bx 1
bx 0
b0 /
bx .
bx -
x,
bx +
x*
x)
b0 (
1'
0&
b0 %
0$
0#
bx "
x!
$end
#5000
0!
b0 "
b0 .
b0 +
b0 1
b0 4
0*
0,
03
b0 -
b0 0
b0 2
1$
#10000
0$
#15000
1$
#20000
0$
0'
#25000
1$
#30000
1)
0$
1&
#35000
b1 +
b1 1
b1 4
1*
1$
#40000
0$
#45000
b1 "
b1 .
1!
b10 +
b10 1
b10 4
b1 -
b1 0
b1 2
1,
13
1$
#50000
0$
#55000
b10 "
b10 .
b10 -
b10 0
b10 2
b11 +
b11 1
b11 4
1$
#60000
0$
#65000
b11 "
b11 .
b100 +
b100 1
b100 4
b11 -
b11 0
b11 2
1$
#70000
0$
#75000
b100 "
b100 .
b100 -
b100 0
b100 2
b101 +
b101 1
b101 4
1$
#80000
0$
b1 %
b1 (
b1 /
#85000
b110 "
b110 .
b110 +
b110 1
b110 4
b110 -
b110 0
b110 2
1$
#90000
0$
#95000
b111 "
b111 .
b111 -
b111 0
b111 2
b111 +
b111 1
b111 4
1$
#100000
0$
#105000
b1000 "
b1000 .
b1000 +
b1000 1
b1000 4
b1000 -
b1000 0
b1000 2
1$
#110000
0$
#115000
b1001 "
b1001 .
b1001 -
b1001 0
b1001 2
b1001 +
b1001 1
b1001 4
1$
#120000
0$
#125000
b1010 "
b1010 .
b1010 +
b1010 1
b1010 4
b1010 -
b1010 0
b1010 2
1$
#130000
0$
b10 %
b10 (
b10 /
#135000
b11110101 "
b11110101 .
b11110101 -
b11110101 0
b11110101 2
b1011 +
b1011 1
b1011 4
1$
#140000
0$
#145000
b11110100 "
b11110100 .
b1100 +
b1100 1
b1100 4
b11110100 -
b11110100 0
b11110100 2
1$
#150000
0$
#155000
b11110011 "
b11110011 .
b11110011 -
b11110011 0
b11110011 2
b1101 +
b1101 1
b1101 4
1$
#160000
0$
#165000
b11110010 "
b11110010 .
b1110 +
b1110 1
b1110 4
b11110010 -
b11110010 0
b11110010 2
1$
#170000
b1110 "
b1110 .
0$
1#
#175000
b1111 "
b1111 .
b11110001 -
b11110001 0
b11110001 2
b1111 +
b1111 1
b1111 4
1$
#180000
0$
#185000
b10000 "
b10000 .
b10000 +
b10000 1
b10000 4
b11110000 -
b11110000 0
b11110000 2
1$
#190000
0$
#195000
b10001 "
b10001 .
b11101111 -
b11101111 0
b11101111 2
b10001 +
b10001 1
b10001 4
1$
#200000
0$
#205000
b10010 "
b10010 .
b10010 +
b10010 1
b10010 4
b11101110 -
b11101110 0
b11101110 2
1$
#210000
0$
#215000
b10011 "
b10011 .
b11101101 -
b11101101 0
b11101101 2
b10011 +
b10011 1
b10011 4
1$
#220000
0$
#225000
b10100 "
b10100 .
b10100 +
b10100 1
b10100 4
b11101100 -
b11101100 0
b11101100 2
1$
#230000
b11101100 "
b11101100 .
0$
b11 %
b11 (
b11 /
0#
#235000
b101000 "
b101000 .
b101000 -
b101000 0
b101000 2
b10101 +
b10101 1
b10101 4
1$
#240000
0$
#245000
b101010 "
b101010 .
b10110 +
b10110 1
b10110 4
b101010 -
b101010 0
b101010 2
1$
#250000
0$
#255000
b101100 "
b101100 .
b101100 -
b101100 0
b101100 2
b10111 +
b10111 1
b10111 4
1$
#260000
0$
#265000
b101110 "
b101110 .
b11000 +
b11000 1
b11000 4
b101110 -
b101110 0
b101110 2
1$
#270000
0)
0$
0&
#275000
1$
#280000
0$
#285000
1$
#290000
0$
#295000
1$
#300000
1)
0$
1&
#305000
b110000 "
b110000 .
b11001 +
b11001 1
b11001 4
b110000 -
b110000 0
b110000 2
1$
#310000
0$
#315000
b110010 "
b110010 .
b110010 -
b110010 0
b110010 2
b11010 +
b11010 1
b11010 4
1$
#320000
0$
#325000
b110100 "
b110100 .
b11011 +
b11011 1
b11011 4
b110100 -
b110100 0
b110100 2
1$
#330000
0$
#335000
b110110 "
b110110 .
b110110 -
b110110 0
b110110 2
b11100 +
b11100 1
b11100 4
1$
#340000
0$
#345000
b111000 "
b111000 .
b11101 +
b11101 1
b11101 4
b111000 -
b111000 0
b111000 2
1$
#350000
0$
#355000
b111010 "
b111010 .
b111010 -
b111010 0
b111010 2
b11110 +
b11110 1
b11110 4
1$
#360000
0$
#365000
b111100 "
b111100 .
b11111 +
b11111 1
b11111 4
b111100 -
b111100 0
b111100 2
1$
#370000
0$
#375000
b111110 "
b111110 .
b111110 -
b111110 0
b111110 2
b100000 +
b100000 1
b100000 4
1$
#380000
0$
#385000
b1000000 "
b1000000 .
b100001 +
b100001 1
b100001 4
b1000000 -
b1000000 0
b1000000 2
1$
#390000
0$
#395000
b1000010 "
b1000010 .
b1000010 -
b1000010 0
b1000010 2
b100010 +
b100010 1
b100010 4
1$
